{"link": [14533, 4788], "path": ["/lib/x86_64-linux-gnu/libc.so.6"], "label": [["PT0"], ["FT0"]], "type": ["SUBJECT_PROCESS", "EVENT_OPEN", "FILE_OBJECT_FILE"]}
{"link": [14533, 4788], "path": ["/lib/x86_64-linux-gnu/libc.so.6"], "label": [["PT0"], ["FT0"]], "type": ["SUBJECT_PROCESS", "EVENT_READ", "FILE_OBJECT_FILE"]}
{"link": [14533, 4788], "path": ["/lib/x86_64-linux-gnu/libc.so.6"], "label": [["PT0"], ["FT0"]], "type": ["SUBJECT_PROCESS", "EVENT_MMAP", "FILE_OBJECT_FILE"]}
{"link": [14533, 18349], "path": "null", "label": [["PT0"], ["MT0"]], "type": ["SUBJECT_PROCESS", "EVENT_MPROTECT", "RECORD_MEMORY_OBJECT"]}
{"link": [14533, 4788], "path": ["/lib/x86_64-linux-gnu/libc.so.6"], "label": [["PT0"], ["FT0"]], "type": ["SUBJECT_PROCESS", "EVENT_MMAP", "FILE_OBJECT_FILE"]}
{"link": [14533, 18351], "path": "null", "label": [["PT0"], ["MT0"]], "type": ["SUBJECT_PROCESS", "EVENT_MMAP", "RECORD_MEMORY_OBJECT"]}
{"link": [14533, 4788], "path": ["/lib/x86_64-linux-gnu/libc.so.6"], "label": [["PT0"], ["FT0"]], "type": ["SUBJECT_PROCESS", "EVENT_CLOSE", "FILE_OBJECT_FILE"]}
{"link": [14533, 4796], "path": ["/lib/x86_64-linux-gnu/libpthread.so.0"], "label": [["PT0"], ["FT0"]], "type": ["SUBJECT_PROCESS", "EVENT_OPEN", "FILE_OBJECT_FILE"]}
{"link": [14533, 4796], "path": ["/lib/x86_64-linux-gnu/libpthread.so.0"], "label": [["PT0"], ["FT0"]], "type": ["SUBJECT_PROCESS", "EVENT_READ", "FILE_OBJECT_FILE"]}
{"link": [14533, 18352], "path": "null", "label": [["PT0"], ["MT0"]], "type": ["SUBJECT_PROCESS", "EVENT_MMAP", "RECORD_MEMORY_OBJECT"]}
{"link": [14533, 4796], "path": ["/lib/x86_64-linux-gnu/libpthread.so.0"], "label": [["PT0"], ["FT0"]], "type": ["SUBJECT_PROCESS", "EVENT_MMAP", "FILE_OBJECT_FILE"]}
{"link": [14533, 18354], "path": "null", "label": [["PT0"], ["MT0"]], "type": ["SUBJECT_PROCESS", "EVENT_MPROTECT", "RECORD_MEMORY_OBJECT"]}
{"link": [14533, 4796], "path": ["/lib/x86_64-linux-gnu/libpthread.so.0"], "label": [["PT0"], ["FT0"]], "type": ["SUBJECT_PROCESS", "EVENT_MMAP", "FILE_OBJECT_FILE"]}
{"link": [14533, 18356], "path": "null", "label": [["PT0"], ["MT0"]], "type": ["SUBJECT_PROCESS", "EVENT_MMAP", "RECORD_MEMORY_OBJECT"]}
{"link": [14533, 4796], "path": ["/lib/x86_64-linux-gnu/libpthread.so.0"], "label": [["PT0"], ["FT0"]], "type": ["SUBJECT_PROCESS", "EVENT_CLOSE", "FILE_OBJECT_FILE"]}
{"link": [14533, 18358], "path": "null", "label": [["PT0"], ["MT0"]], "type": ["SUBJECT_PROCESS", "EVENT_MMAP", "RECORD_MEMORY_OBJECT"]}
{"link": [14533, 18359], "path": "null", "label": [["PT0"], ["MT0"]], "type": ["SUBJECT_PROCESS", "EVENT_MMAP", "RECORD_MEMORY_OBJECT"]}
{"link": [14533, 18360], "path": "null", "label": [["PT0"], ["MT0"]], "type": ["SUBJECT_PROCESS", "EVENT_MMAP", "RECORD_MEMORY_OBJECT"]}
{"link": [14533, 18364], "path": "null", "label": [["PT0"], ["MT0"]], "type": ["SUBJECT_PROCESS", "EVENT_MPROTECT", "RECORD_MEMORY_OBJECT"]}
{"link": [14533, 18367], "path": "null", "label": [["PT0"], ["MT0"]], "type": ["SUBJECT_PROCESS", "EVENT_MPROTECT", "RECORD_MEMORY_OBJECT"]}
{"link": [14533, 18368], "path": "null", "label": [["PT0"], ["MT0"]], "type": ["SUBJECT_PROCESS", "EVENT_MPROTECT", "RECORD_MEMORY_OBJECT"]}
{"link": [14533, 18370], "path": "null", "label": [["PT0"], ["MT0"]], "type": ["SUBJECT_PROCESS", "EVENT_MPROTECT", "RECORD_MEMORY_OBJECT"]}
{"link": [14533, 18372], "path": "null", "label": [["PT0"], ["MT0"]], "type": ["SUBJECT_PROCESS", "EVENT_MPROTECT", "RECORD_MEMORY_OBJECT"]}
{"link": [14533, 18373], "path": "null", "label": [["PT0"], ["MT0"]], "type": ["SUBJECT_PROCESS", "EVENT_MPROTECT", "RECORD_MEMORY_OBJECT"]}
