{"link": [23331, 72356], "path": "null", "label": [["PT3"], ["MT0"]], "type": ["SUBJECT_PROCESS", "EVENT_MPROTECT", "RECORD_MEMORY_OBJECT"]}
{"link": [23331, 72358], "path": "null", "label": [["PT3"], ["MT0"]], "type": ["SUBJECT_PROCESS", "EVENT_MMAP", "RECORD_MEMORY_OBJECT"]}
{"link": [23331, 72359], "path": "null", "label": [["PT3"], ["MT0"]], "type": ["SUBJECT_PROCESS", "EVENT_MMAP", "RECORD_MEMORY_OBJECT"]}
{"link": [23331, 72360], "path": "null", "label": [["PT3"], ["MT0"]], "type": ["SUBJECT_PROCESS", "EVENT_MMAP", "RECORD_MEMORY_OBJECT"]}
{"link": [23331, 72361], "path": "null", "label": [["PT3"], ["MT0"]], "type": ["SUBJECT_PROCESS", "EVENT_MPROTECT", "RECORD_MEMORY_OBJECT"]}
{"link": [23331, 72362], "path": "null", "label": [["PT3"], ["MT0"]], "type": ["SUBJECT_PROCESS", "EVENT_MPROTECT", "RECORD_MEMORY_OBJECT"]}
{"link": [23331, 72363], "path": "null", "label": [["PT3"], ["MT0"]], "type": ["SUBJECT_PROCESS", "EVENT_MPROTECT", "RECORD_MEMORY_OBJECT"]}
