{"link": [26005, 4785], "path": ["/lib64/ld-linux-x86-64.so.2"], "label": [["PT97", "PT3"], ["FT0"]], "type": ["SUBJECT_PROCESS", "EVENT_LOADLIBRARY", "FILE_OBJECT_FILE"]}
{"link": [26005, 4824], "path": ["/bin/sed"], "label": [["PT97", "PT3"], ["FT0"]], "type": ["SUBJECT_PROCESS", "EVENT_LOADLIBRARY", "FILE_OBJECT_FILE"]}
{"link": [26005, 4787], "path": ["/etc/ld.so.cache"], "label": [["PT97", "PT3"], ["FT0"]], "type": ["SUBJECT_PROCESS", "EVENT_OPEN", "FILE_OBJECT_FILE"]}
{"link": [26005, 4787], "path": ["/etc/ld.so.cache"], "label": [["PT97", "PT3"], ["FT0"]], "type": ["SUBJECT_PROCESS", "EVENT_MMAP", "FILE_OBJECT_FILE"]}
{"link": [26005, 4787], "path": ["/etc/ld.so.cache"], "label": [["PT97", "PT3"], ["FT0"]], "type": ["SUBJECT_PROCESS", "EVENT_CLOSE", "FILE_OBJECT_FILE"]}
{"link": [26005, 4825], "path": ["/lib/x86_64-linux-gnu/libselinux.so.1"], "label": [["PT97", "PT3"], ["FT0"]], "type": ["SUBJECT_PROCESS", "EVENT_OPEN", "FILE_OBJECT_FILE"]}
{"link": [26005, 4825], "path": ["/lib/x86_64-linux-gnu/libselinux.so.1"], "label": [["PT97", "PT3"], ["FT0"]], "type": ["SUBJECT_PROCESS", "EVENT_READ", "FILE_OBJECT_FILE"]}
{"link": [26005, 88518], "path": "null", "label": [["PT97", "PT3"], ["MT0"]], "type": ["SUBJECT_PROCESS", "EVENT_MMAP", "RECORD_MEMORY_OBJECT"]}
{"link": [26005, 4825], "path": ["/lib/x86_64-linux-gnu/libselinux.so.1"], "label": [["PT97", "PT3"], ["FT0"]], "type": ["SUBJECT_PROCESS", "EVENT_MMAP", "FILE_OBJECT_FILE"]}
{"link": [26005, 88520], "path": "null", "label": [["PT97", "PT3"], ["MT0"]], "type": ["SUBJECT_PROCESS", "EVENT_MPROTECT", "RECORD_MEMORY_OBJECT"]}
{"link": [26005, 4825], "path": ["/lib/x86_64-linux-gnu/libselinux.so.1"], "label": [["PT97", "PT3"], ["FT0"]], "type": ["SUBJECT_PROCESS", "EVENT_MMAP", "FILE_OBJECT_FILE"]}
{"link": [26005, 88522], "path": "null", "label": [["PT97", "PT3"], ["MT0"]], "type": ["SUBJECT_PROCESS", "EVENT_MMAP", "RECORD_MEMORY_OBJECT"]}
{"link": [26005, 4825], "path": ["/lib/x86_64-linux-gnu/libselinux.so.1"], "label": [["PT97", "PT3"], ["FT0"]], "type": ["SUBJECT_PROCESS", "EVENT_CLOSE", "FILE_OBJECT_FILE"]}
{"link": [26005, 4788], "path": ["/lib/x86_64-linux-gnu/libc.so.6"], "label": [["PT97", "PT3"], ["FT0"]], "type": ["SUBJECT_PROCESS", "EVENT_OPEN", "FILE_OBJECT_FILE"]}
{"link": [26005, 4788], "path": ["/lib/x86_64-linux-gnu/libc.so.6"], "label": [["PT97", "PT3"], ["FT0"]], "type": ["SUBJECT_PROCESS", "EVENT_READ", "FILE_OBJECT_FILE"]}
{"link": [26005, 4788], "path": ["/lib/x86_64-linux-gnu/libc.so.6"], "label": [["PT97", "PT3"], ["FT0"]], "type": ["SUBJECT_PROCESS", "EVENT_MMAP", "FILE_OBJECT_FILE"]}
{"link": [26005, 88524], "path": "null", "label": [["PT97", "PT3"], ["MT0"]], "type": ["SUBJECT_PROCESS", "EVENT_MPROTECT", "RECORD_MEMORY_OBJECT"]}
{"link": [26005, 4788], "path": ["/lib/x86_64-linux-gnu/libc.so.6"], "label": [["PT97", "PT3"], ["FT0"]], "type": ["SUBJECT_PROCESS", "EVENT_MMAP", "FILE_OBJECT_FILE"]}
{"link": [26005, 88526], "path": "null", "label": [["PT97", "PT3"], ["MT0"]], "type": ["SUBJECT_PROCESS", "EVENT_MMAP", "RECORD_MEMORY_OBJECT"]}
{"link": [26005, 4788], "path": ["/lib/x86_64-linux-gnu/libc.so.6"], "label": [["PT97", "PT3"], ["FT0"]], "type": ["SUBJECT_PROCESS", "EVENT_CLOSE", "FILE_OBJECT_FILE"]}
{"link": [26005, 4790], "path": ["/lib/x86_64-linux-gnu/libpcre.so.3"], "label": [["PT97", "PT3"], ["FT0"]], "type": ["SUBJECT_PROCESS", "EVENT_OPEN", "FILE_OBJECT_FILE"]}
{"link": [26005, 4790], "path": ["/lib/x86_64-linux-gnu/libpcre.so.3"], "label": [["PT97", "PT3"], ["FT0"]], "type": ["SUBJECT_PROCESS", "EVENT_READ", "FILE_OBJECT_FILE"]}
{"link": [26005, 4790], "path": ["/lib/x86_64-linux-gnu/libpcre.so.3"], "label": [["PT97", "PT3"], ["FT0"]], "type": ["SUBJECT_PROCESS", "EVENT_MMAP", "FILE_OBJECT_FILE"]}
{"link": [26005, 88528], "path": "null", "label": [["PT97", "PT3"], ["MT0"]], "type": ["SUBJECT_PROCESS", "EVENT_MPROTECT", "RECORD_MEMORY_OBJECT"]}
{"link": [26005, 4790], "path": ["/lib/x86_64-linux-gnu/libpcre.so.3"], "label": [["PT97", "PT3"], ["FT0"]], "type": ["SUBJECT_PROCESS", "EVENT_MMAP", "FILE_OBJECT_FILE"]}
{"link": [26005, 4790], "path": ["/lib/x86_64-linux-gnu/libpcre.so.3"], "label": [["PT97", "PT3"], ["FT0"]], "type": ["SUBJECT_PROCESS", "EVENT_CLOSE", "FILE_OBJECT_FILE"]}
{"link": [26005, 4797], "path": ["/lib/x86_64-linux-gnu/libdl.so.2"], "label": [["PT97", "PT3"], ["FT0"]], "type": ["SUBJECT_PROCESS", "EVENT_OPEN", "FILE_OBJECT_FILE"]}
{"link": [26005, 4797], "path": ["/lib/x86_64-linux-gnu/libdl.so.2"], "label": [["PT97", "PT3"], ["FT0"]], "type": ["SUBJECT_PROCESS", "EVENT_READ", "FILE_OBJECT_FILE"]}
{"link": [26005, 88530], "path": "null", "label": [["PT97", "PT3"], ["MT0"]], "type": ["SUBJECT_PROCESS", "EVENT_MMAP", "RECORD_MEMORY_OBJECT"]}
{"link": [26005, 4797], "path": ["/lib/x86_64-linux-gnu/libdl.so.2"], "label": [["PT97", "PT3"], ["FT0"]], "type": ["SUBJECT_PROCESS", "EVENT_MMAP", "FILE_OBJECT_FILE"]}
{"link": [26005, 88532], "path": "null", "label": [["PT97", "PT3"], ["MT0"]], "type": ["SUBJECT_PROCESS", "EVENT_MPROTECT", "RECORD_MEMORY_OBJECT"]}
{"link": [26005, 4797], "path": ["/lib/x86_64-linux-gnu/libdl.so.2"], "label": [["PT97", "PT3"], ["FT0"]], "type": ["SUBJECT_PROCESS", "EVENT_MMAP", "FILE_OBJECT_FILE"]}
{"link": [26005, 4797], "path": ["/lib/x86_64-linux-gnu/libdl.so.2"], "label": [["PT97", "PT3"], ["FT0"]], "type": ["SUBJECT_PROCESS", "EVENT_CLOSE", "FILE_OBJECT_FILE"]}
{"link": [26005, 4796], "path": ["/lib/x86_64-linux-gnu/libpthread.so.0"], "label": [["PT97", "PT3"], ["FT0"]], "type": ["SUBJECT_PROCESS", "EVENT_OPEN", "FILE_OBJECT_FILE"]}
{"link": [26005, 4796], "path": ["/lib/x86_64-linux-gnu/libpthread.so.0"], "label": [["PT97", "PT3"], ["FT0"]], "type": ["SUBJECT_PROCESS", "EVENT_READ", "FILE_OBJECT_FILE"]}
{"link": [26005, 4796], "path": ["/lib/x86_64-linux-gnu/libpthread.so.0"], "label": [["PT97", "PT3"], ["FT0"]], "type": ["SUBJECT_PROCESS", "EVENT_MMAP", "FILE_OBJECT_FILE"]}
{"link": [26005, 88535], "path": "null", "label": [["PT97", "PT3"], ["MT0"]], "type": ["SUBJECT_PROCESS", "EVENT_MPROTECT", "RECORD_MEMORY_OBJECT"]}
{"link": [26005, 4796], "path": ["/lib/x86_64-linux-gnu/libpthread.so.0"], "label": [["PT97", "PT3"], ["FT0"]], "type": ["SUBJECT_PROCESS", "EVENT_MMAP", "FILE_OBJECT_FILE"]}
{"link": [26005, 88537], "path": "null", "label": [["PT97", "PT3"], ["MT0"]], "type": ["SUBJECT_PROCESS", "EVENT_MMAP", "RECORD_MEMORY_OBJECT"]}
{"link": [26005, 4796], "path": ["/lib/x86_64-linux-gnu/libpthread.so.0"], "label": [["PT97", "PT3"], ["FT0"]], "type": ["SUBJECT_PROCESS", "EVENT_CLOSE", "FILE_OBJECT_FILE"]}
{"link": [26005, 88538], "path": "null", "label": [["PT97", "PT3"], ["MT0"]], "type": ["SUBJECT_PROCESS", "EVENT_MMAP", "RECORD_MEMORY_OBJECT"]}
{"link": [26005, 88539], "path": "null", "label": [["PT97", "PT3"], ["MT0"]], "type": ["SUBJECT_PROCESS", "EVENT_MMAP", "RECORD_MEMORY_OBJECT"]}
{"link": [26005, 88540], "path": "null", "label": [["PT97", "PT3"], ["MT0"]], "type": ["SUBJECT_PROCESS", "EVENT_MPROTECT", "RECORD_MEMORY_OBJECT"]}
{"link": [26005, 88541], "path": "null", "label": [["PT97", "PT3"], ["MT0"]], "type": ["SUBJECT_PROCESS", "EVENT_MPROTECT", "RECORD_MEMORY_OBJECT"]}
{"link": [26005, 88542], "path": "null", "label": [["PT97", "PT3"], ["MT0"]], "type": ["SUBJECT_PROCESS", "EVENT_MPROTECT", "RECORD_MEMORY_OBJECT"]}
{"link": [26005, 88543], "path": "null", "label": [["PT97", "PT3"], ["MT0"]], "type": ["SUBJECT_PROCESS", "EVENT_MPROTECT", "RECORD_MEMORY_OBJECT"]}
{"link": [26005, 88544], "path": "null", "label": [["PT97", "PT3"], ["MT0"]], "type": ["SUBJECT_PROCESS", "EVENT_MPROTECT", "RECORD_MEMORY_OBJECT"]}
{"link": [26005, 88545], "path": "null", "label": [["PT97", "PT3"], ["MT0"]], "type": ["SUBJECT_PROCESS", "EVENT_MPROTECT", "RECORD_MEMORY_OBJECT"]}
{"link": [26005, 88546], "path": "null", "label": [["PT97", "PT3"], ["MT0"]], "type": ["SUBJECT_PROCESS", "EVENT_MPROTECT", "RECORD_MEMORY_OBJECT"]}
{"link": [26005, 4826], "path": ["/proc/filesystems"], "label": [["PT97", "PT3"], ["FT0"]], "type": ["SUBJECT_PROCESS", "EVENT_OPEN", "FILE_OBJECT_FILE"]}
{"link": [26005, 4826], "path": ["/proc/filesystems"], "label": [["PT97", "PT3"], ["FT0"]], "type": ["SUBJECT_PROCESS", "EVENT_READ", "FILE_OBJECT_FILE"]}
{"link": [26005, 4826], "path": ["/proc/filesystems"], "label": [["PT97", "PT3"], ["FT0"]], "type": ["SUBJECT_PROCESS", "EVENT_READ", "FILE_OBJECT_FILE"]}
{"link": [26005, 4826], "path": ["/proc/filesystems"], "label": [["PT97", "PT3"], ["FT0"]], "type": ["SUBJECT_PROCESS", "EVENT_CLOSE", "FILE_OBJECT_FILE"]}
