{"link": [26232, 89433], "path": "null", "label": [["PT3"], ["MT0"]], "type": ["SUBJECT_PROCESS", "EVENT_MMAP", "RECORD_MEMORY_OBJECT"]}
{"link": [26232, 89435], "path": "null", "label": [["PT3"], ["MT0"]], "type": ["SUBJECT_PROCESS", "EVENT_MPROTECT", "RECORD_MEMORY_OBJECT"]}
{"link": [26232, 89437], "path": "null", "label": [["PT3"], ["MT0"]], "type": ["SUBJECT_PROCESS", "EVENT_MMAP", "RECORD_MEMORY_OBJECT"]}
{"link": [26232, 89438], "path": "null", "label": [["PT3"], ["MT0"]], "type": ["SUBJECT_PROCESS", "EVENT_MMAP", "RECORD_MEMORY_OBJECT"]}
{"link": [26232, 89439], "path": "null", "label": [["PT3"], ["MT0"]], "type": ["SUBJECT_PROCESS", "EVENT_MMAP", "RECORD_MEMORY_OBJECT"]}
{"link": [26232, 89440], "path": "null", "label": [["PT3"], ["MT0"]], "type": ["SUBJECT_PROCESS", "EVENT_MPROTECT", "RECORD_MEMORY_OBJECT"]}
{"link": [26232, 89441], "path": "null", "label": [["PT3"], ["MT0"]], "type": ["SUBJECT_PROCESS", "EVENT_MPROTECT", "RECORD_MEMORY_OBJECT"]}
{"link": [26232, 89442], "path": "null", "label": [["PT3"], ["MT0"]], "type": ["SUBJECT_PROCESS", "EVENT_MPROTECT", "RECORD_MEMORY_OBJECT"]}
